NEMtropy/__init__.py
NEMtropy/ensemble_functions.py
NEMtropy/ensemble_generator.py
NEMtropy/graph_classes.py
NEMtropy/matrix_generator.py
NEMtropy/models_functions.py
NEMtropy/network_functions.py
NEMtropy/poibin.py
NEMtropy/solver_functions.py
NEMtropy-3.0.3.dist-info/LICENSE.txt
NEMtropy-3.0.3.dist-info/METADATA
NEMtropy-3.0.3.dist-info/WHEEL
NEMtropy-3.0.3.dist-info/top_level.txt
NEMtropy-3.0.3.dist-info/RECORD
