Metadata-Version: 2.1
Name: NEMtropy
Version: 3.0.3
Summary: NEMtropy is a Maximum-Entropy toolbox for networks, it provides the user with a state of the art solver for a range variety of Maximum Entropy Networks models derived from the ERGM family. This module allows you to solve the desired model and generate a number of randomized graphs from the original one: the so-called graphs ensemble.
Home-page: https://github.com/nicoloval/NEMtropy/
Download-URL: https://github.com/nicoloval/NEMtropy/archive/refs/tags/v2.1.1.zip
Author: Nicolo' Vallarano, Emiliano Marchese, Matteo Bruno
Author-email: nico.vallarano@gmail.com, emilianomarcheserc@gmail.com, matteobruno180@gmail.com
License: GNU General Public License v3
Keywords: Network reconstruction,Networks Null Models,Maximum Entropy Methods
Classifier: License :: OSI Approved :: GNU Library or Lesser General Public License (LGPL)
Classifier: Programming Language :: Python :: 3
Classifier: Programming Language :: Python :: 3.5
Classifier: Programming Language :: Python :: 3.6
Classifier: Programming Language :: Python :: 3.7
Classifier: Programming Language :: Python :: 3.8
License-File: LICENSE.txt
Requires-Dist: numpy (>=1.17)
Requires-Dist: scipy (>=1.4)
Requires-Dist: networkx (>=2.4)
Requires-Dist: powerlaw (>=1.4)
Requires-Dist: tqdm (>=4.5)
Requires-Dist: bicm (>=3.2.0)
Provides-Extra: dev
Requires-Dist: pytest (>=6.0.1) ; extra == 'dev'
Requires-Dist: flake8 (>=3.8.3) ; extra == 'dev'
Requires-Dist: wheel (>=0.35.1) ; extra == 'dev'
Requires-Dist: check-manifest (>=0.44) ; extra == 'dev'
Requires-Dist: setuptools (>=47.1.0) ; extra == 'dev'
Requires-Dist: twine (>=3.2.0) ; extra == 'dev'
Requires-Dist: tox (>=3.20.1) ; extra == 'dev'
Requires-Dist: powerlaw (>=1.4.4) ; extra == 'dev'
